raingbow/__init__.py
raingbow/raingbow.py
raingbow-1.1.dist-info/LICENSE
raingbow-1.1.dist-info/METADATA
raingbow-1.1.dist-info/WHEEL
raingbow-1.1.dist-info/top_level.txt
raingbow-1.1.dist-info/RECORD
