Metadata-Version: 2.1
Name: raingbow
Version: 1.1
Summary: Module for rough translation of visible light wavelength values to RGB-color values
Home-page: UNKNOWN
Author: Max Saganyuk
Author-email: makssagan1@mail.ru
License: UNKNOWN
Platform: UNKNOWN
Classifier: Programming Language :: Python :: 3
Classifier: License :: OSI Approved :: MIT License
Classifier: Operating System :: OS Independent
Requires-Python: >=3.6
